sumo_gym/__init__.py
sumo_gym/plot.py
sumo_gym/typing.py
sumo_gym/envs/__init__.py
sumo_gym/envs/fmp.py
sumo_gym/spaces/__init__.py
sumo_gym/spaces/grid.py
sumo_gym/spaces/network.py
sumo_gym/utils/__init__.py
sumo_gym/utils/fmp_utils.py
sumo_gym/utils/network_utils.py
sumo_gym/utils/sumo_utils.py
sumo_gym/utils/svg_uitls.py
sumo_gym/utils/xml_utils.py
sumo_gym-0.5.0.dist-info/LICENSE
sumo_gym-0.5.0.dist-info/METADATA
sumo_gym-0.5.0.dist-info/WHEEL
sumo_gym-0.5.0.dist-info/top_level.txt
sumo_gym-0.5.0.dist-info/RECORD
