Metadata-Version: 2.1
Name: sumo-gym
Version: 0.5.0
Summary: OpenAI-gym like toolkit for developing and comparing reinforcement learning algorithms on SUMO
Home-page: https://github.com/lovelybuggies/sumo-gym
Author: Shuo Liu
Author-email: ninomyemail@gmail.com
License: UNKNOWN
Platform: UNKNOWN
Classifier: Programming Language :: Python :: 3
Classifier: License :: OSI Approved :: Mozilla Public License 2.0 (MPL 2.0)
Classifier: Operating System :: OS Independent
Requires-Python: >=3.7
License-File: LICENSE
Requires-Dist: gym
Provides-Extra: all
Requires-Dist: Sphinx (>=3.0.0) ; extra == 'all'
Requires-Dist: ipykernel ; extra == 'all'
Requires-Dist: ipython ; extra == 'all'
Requires-Dist: matplotlib (>=3.0) ; extra == 'all'
Requires-Dist: nbsphinx ; extra == 'all'
Requires-Dist: pytest (>=6) ; extra == 'all'
Requires-Dist: pytest-mpl (>=0.12) ; extra == 'all'
Requires-Dist: sphinx-book-theme (>=0.0.38) ; extra == 'all'
Requires-Dist: sphinx-copybutton ; extra == 'all'
Requires-Dist: sphinx-rtd-theme (>=0.5.0) ; extra == 'all'
Requires-Dist: torch (>=1.10.0) ; extra == 'all'
Requires-Dist: torchaudio (>=0.10.0) ; extra == 'all'
Requires-Dist: torchvision (>=0.11.1) ; extra == 'all'
Provides-Extra: dev
Requires-Dist: pytest (>=6) ; extra == 'dev'
Requires-Dist: pytest-mpl (>=0.12) ; extra == 'dev'
Requires-Dist: matplotlib (>=3.0) ; extra == 'dev'
Requires-Dist: torch (>=1.10.0) ; extra == 'dev'
Requires-Dist: torchvision (>=0.11.1) ; extra == 'dev'
Requires-Dist: torchaudio (>=0.10.0) ; extra == 'dev'
Requires-Dist: ipykernel ; extra == 'dev'
Provides-Extra: docs
Requires-Dist: matplotlib (>=3.0) ; extra == 'docs'
Requires-Dist: nbsphinx ; extra == 'docs'
Requires-Dist: Sphinx (>=3.0.0) ; extra == 'docs'
Requires-Dist: sphinx-copybutton ; extra == 'docs'
Requires-Dist: sphinx-rtd-theme (>=0.5.0) ; extra == 'docs'
Requires-Dist: sphinx-book-theme (>=0.0.38) ; extra == 'docs'
Requires-Dist: ipython ; extra == 'docs'
Requires-Dist: ipykernel ; extra == 'docs'
Provides-Extra: plot
Requires-Dist: matplotlib (>=3.0) ; extra == 'plot'
Provides-Extra: test
Requires-Dist: pytest (>=6) ; extra == 'test'
Requires-Dist: pytest-mpl (>=0.12) ; extra == 'test'
Provides-Extra: torch
Requires-Dist: torch (>=1.10.0) ; extra == 'torch'
Requires-Dist: torchvision (>=0.11.1) ; extra == 'torch'
Requires-Dist: torchaudio (>=0.10.0) ; extra == 'torch'
